{
    "entries": [
        {
            "name": "init",
            "text": "",
            "response": "",
            "function": "moveOnCompleteQuest::bigFatMelon,melonCompleted,init2",
            "children": []
        },
        {
            "name": "init2",
            "text": "Hello, traveller.",
            "response": "",
            "function": "",
            "children": [
                {
                    "name": "hello",
                    "text": "Hey @npc.",
                    "response": "How did you know my name?",
                    "function": "",
                    "children": [
                        {
                            "name": "visible",
                            "text": "Well, I can see it. Right there above your head.",
                            "response": "Oh.",
                            "function": "",
                            "children": [
                                {
                                    "name": "inquiry",
                                    "text": "Anything I should know about the place?",
                                    "response": "Not really. We're a small fishing port. And we mainly keep to ourselves. Have you talked to Mollie yet?",
                                    "function": "",
                                    "children": [
                                        {
                                            "name": "yes",
                                            "text": "I did!",
                                            "response": "Wonderful old gal, right? Well, if you like talking to people, there's others. Farmer Ham, for one, just up past the pub and across the walkway. Chat him up.",
                                            "function": "",
                                            "children": [
                                                {
                                                    "name": "willdo",
                                                    "text": "Will do!",
                                                    "response": "Oh, and be sure to check out the library here, just to your right.",
                                                    "function": "",
                                                    "children": []
                                                }
                                            ]
                                        },
                                        {
                                            "name": "notYet",
                                            "text": "Not yet.",
                                            "response": "Well, be sure to, if you get the chance. She's in the office down by the dock. And there's also Farmer Ham, past the pub and down the walkway. I'd go see them both.",
                                            "function": "",
                                            "children": [
                                                {
                                                    "name": "willdo2",
                                                    "text": "Will do!",
                                                    "response": "Oh, and be sure to check out the library here, just to your right.",
                                                    "function": "",
                                                    "children": []
                                                }
                                            ]
                                        },
                                        {
                                            "name": "who",
                                            "text": "Who?",
                                            "response": "Mollie, down by the office. There's also Farmer Ham's place, up past the pub and across the walkway. Be sure to visit them both.",
                                            "function": "",
                                            "children": [
                                                {
                                                    "name": "willdo3",
                                                    "text": "Will do!",
                                                    "response": "Oh, and be sure to check out the library here, just to your right.",
                                                    "function": "",
                                                    "children": []
                                                }
                                            ]
                                        }
                                    ]
                                }
                            ]
                        }
                    ]
                }
            ]
        },
        {
            "name": "melonCompleted",
            "text": "Welcome! Talked to Old Zedd yet?",
            "response": "",
            "function": "",
            "children": []
        }
    ]
}